{
  "meta": {
    "description": "This file lists the nodes that connect the train track layout pieces. Track pieces are in separate file."
  },
  "nodes": {
    "1": {
      "coordinate": {
        "x": 9735,
        "y": 7710
      }
    },
    "2": {
      "coordinate": {
        "x": 9735,
        "y": 8310
      }
    },
    "3": {
      "coordinate": {
        "x": 9735,
        "y": 8910
      }
    },
    "4": {
      "coordinate": {
        "x": 9815.38476,
        "y": 9210
      }
    },
    "5": {
      "coordinate": {
        "x": 10035,
        "y": 9429.61524
      }
    },
    "6": {
      "coordinate": {
        "x": 10335,
        "y": 9510
      }
    },
    "7": {
      "coordinate": {
        "x": 10935,
        "y": 9510
      }
    },
    "8": {
      "coordinate": {
        "x": 11392.3067,
        "y": 9419.03604
      }
    },
    "9": {
      "coordinate": {
        "x": 11779.9926,
        "y": 9159.9926
      }
    },
    "10": {
      "coordinate": {
        "x": 12039.03604,
        "y": 8772.3067
      }
    },
    "11": {
      "coordinate": {
        "x": 12130,
        "y": 8315
      }
    },
    "12": {
      "coordinate": {
        "x": 12130,
        "y": 8015
      }
    },
    "13": {
      "coordinate": {
        "x": 12130,
        "y": 7715
      }
    }
  }
}